zotcher/__init__.py
zotcher/api.py
zotcher/configurator.py
zotcher/constants.py
zotcher/payload.py
zotcher/runner.py
zotcher/utils.py
zotcher-0.0.3.dist-info/LICENSE
zotcher-0.0.3.dist-info/METADATA
zotcher-0.0.3.dist-info/WHEEL
zotcher-0.0.3.dist-info/entry_points.txt
zotcher-0.0.3.dist-info/top_level.txt
zotcher-0.0.3.dist-info/RECORD
