Metadata-Version: 2.1
Name: zotcher
Version: 0.0.3
Summary: A simple (unofficial) Zomato Partner API client library & CLI
Home-page: https://github.com/mentix02/zotcher
Author: Manan
Author-email: manan.yadav02@gmail.com
License: GPLv3
Project-URL: Homepage, https://github.com/mentix02/zotcher
Project-URL: Bug Tracker, https://github.com/mentix02/zotcher/issues
Keywords: zomato api cli partner
Classifier: Topic :: Internet :: WWW/HTTP
Classifier: Topic :: Software Development :: Libraries
Classifier: Programming Language :: Python :: 3
Classifier: Programming Language :: Python :: 3.9
Classifier: Programming Language :: Python :: 3.10
Classifier: Programming Language :: Python :: 3.11
Classifier: Programming Language :: Python :: 3.12
Classifier: Programming Language :: Python :: 3 :: Only
Classifier: License :: OSI Approved :: GNU General Public License v3 (GPLv3)
Requires-Python: >=3.9
License-File: LICENSE
Requires-Dist: requests (>=2.28.1)
